tkitTagger/__init__.py
tkitTagger/model.py
tkitTagger-0.0.0.2.16340988.dist-info/LICENSE
tkitTagger-0.0.0.2.16340988.dist-info/METADATA
tkitTagger-0.0.0.2.16340988.dist-info/WHEEL
tkitTagger-0.0.0.2.16340988.dist-info/top_level.txt
tkitTagger-0.0.0.2.16340988.dist-info/RECORD
